benchalerts/__init__.py
benchalerts/_version.py
benchalerts/alert_pipeline.py
benchalerts/conbench_dataclasses.py
benchalerts/message_formatting.py
benchalerts/integrations/__init__.py
benchalerts/integrations/github.py
benchalerts/integrations/slack.py
benchalerts/pipeline_steps/__init__.py
benchalerts/pipeline_steps/conbench.py
benchalerts/pipeline_steps/github.py
benchalerts/pipeline_steps/slack.py
benchalerts-2024.1.10.1.dist-info/METADATA
benchalerts-2024.1.10.1.dist-info/WHEEL
benchalerts-2024.1.10.1.dist-info/top_level.txt
benchalerts-2024.1.10.1.dist-info/RECORD
