Metadata-Version: 2.1
Name: benchalerts
Version: 2024.1.10.1
Summary: Automated alerting for conbench
Home-page: https://github.com/conbench/benchalerts
Maintainer: Austin Dickey
Maintainer-email: austin@voltrondata.com
Classifier: Programming Language :: Python :: 3.8
Classifier: License :: OSI Approved :: Apache Software License
Requires-Python: >=3.8
Requires-Dist: benchclients >=2023.2.24
Requires-Dist: pyjwt[crypto]
Provides-Extra: dev
Requires-Dist: pytest ; extra == 'dev'
